README.md
setup.py
facemask/__init__.py
facemask/api.py
facemask/version.py
facemask.egg-info/PKG-INFO
facemask.egg-info/SOURCES.txt
facemask.egg-info/dependency_links.txt
facemask.egg-info/not-zip-safe
facemask.egg-info/requires.txt
facemask.egg-info/top_level.txt
facemask/model/__init__.py
facemask/model/decode.py
facemask/model/mobilenet_v2.py
facemask/model/model.py
facemask/utils/__init__.py
facemask/utils/config.py
facemask/utils/image.py
facemask/utils/util.py