Metadata-Version: 2.1
Name: facemask
Version: 0.1.1
Summary: Face Mask detection
Home-page: https://github.com/chenjun2hao/facemask
Author: Jun Chen
Author-email: 778961303@qq.com
License: MIT
Keywords: computer vision
Platform: UNKNOWN
Classifier: Programming Language :: Python :: 3.6
